oarepo_references_draft/__init__.py
oarepo_references_draft/ext.py
oarepo_references_draft/version.py
oarepo_references_draft-1.1.0.dist-info/AUTHORS.rst
oarepo_references_draft-1.1.0.dist-info/LICENSE
oarepo_references_draft-1.1.0.dist-info/METADATA
oarepo_references_draft-1.1.0.dist-info/WHEEL
oarepo_references_draft-1.1.0.dist-info/entry_points.txt
oarepo_references_draft-1.1.0.dist-info/top_level.txt
oarepo_references_draft-1.1.0.dist-info/RECORD
