Metadata-Version: 2.1
Name: oarepo-references-draft
Version: 1.1.0
Summary: OArepo module for tracking and updating references in Invenio records.
Home-page: https://github.com/oarepo/oarepo-references-draft
Author: Mirek Simek, VSCHT Praha
Author-email: miroslav.simek@vscht.cz
License: MIT
Platform: any
Classifier: Environment :: Web Environment
Classifier: Intended Audience :: Developers
Classifier: License :: OSI Approved :: MIT License
Classifier: Operating System :: OS Independent
Classifier: Programming Language :: Python
Classifier: Topic :: Internet :: WWW/HTTP :: Dynamic Content
Classifier: Topic :: Software Development :: Libraries :: Python Modules
Classifier: Programming Language :: Python :: 2
Classifier: Programming Language :: Python :: 2.7
Classifier: Programming Language :: Python :: 3
Classifier: Programming Language :: Python :: 3.5
Classifier: Development Status :: 4 - Beta
Requires-Dist: oarepo-invenio-records-draft (>=3.0.0)
Requires-Dist: oarepo-references (>=1.4.3)
Provides-Extra: docs
Requires-Dist: Sphinx (>=1.5.1) ; extra == 'docs'
Provides-Extra: tests
Requires-Dist: oarepo[tests] (~=3.2.0a9) ; extra == 'tests'
Provides-Extra: tests-es7
Requires-Dist: oarepo[tests-es7] (~=3.2.0a9) ; extra == 'tests-es7'
